ttwizz/__init__.py
ttwizz/ttwizz.py
ttwizz-2.0.0.dist-info/LICENSE
ttwizz-2.0.0.dist-info/METADATA
ttwizz-2.0.0.dist-info/WHEEL
ttwizz-2.0.0.dist-info/top_level.txt
ttwizz-2.0.0.dist-info/RECORD
