Metadata-Version: 2.1
Name: ttwizz
Version: 2.0.0
Summary: Registers an always-on web server.
Home-page: https://github.com/ttwizz
Author: ttwiz_z
Author-email: moderkascriptsltd@gmail.com
Project-URL: Organization, https://github.com/ModerkaScripts
Keywords: ttwizz
Classifier: Programming Language :: Python :: 3.10
Classifier: License :: OSI Approved :: MIT License
Classifier: Operating System :: OS Independent
Requires-Python: >=3.8
License-File: LICENSE
Requires-Dist: Flask (>=1.1.2)
